{
    "rules": [
        {
            "trigger": "keyword",
            "keyword": "bananas",
            "response": "I think that's just bananas!"
        },
        {
            "command": "test",
            "description": "Test command",
            "trigger": "command",
            "response": "Hello world!"
        },
        {
            "command": "cat",
            "description": "List breeds of cats and their IDs, check info or get an image of a random or specified breed, or random gifs of cats.",
            "usage": [
                "breeds",
                "info [random|<breed ID>]",
                "image [random|<breed ID>]",
                "gif"
            ],
            "trigger": "command",
            "class": "CatAPI"
        },
        {
            "command": "dog",
            "description": "List breeds of dogs, or get an image of a random or specified breed.",
            "usage": [
                "breeds",
                "image [random|<breed> <sub-breed (optional)>]"
            ],
            "trigger": "command",
            "class": "DogAPI"
        },
        {
            "command": "list",
            "description": "List all available commands.",
            "usage": "",
            "trigger": "command",
            "class": "List"
        }
    ]
}